hypothesis_torch/__init__.py
hypothesis_torch/device.py
hypothesis_torch/dtype.py
hypothesis_torch/huggingface.py
hypothesis_torch/inspection_util.py
hypothesis_torch/layout.py
hypothesis_torch/memory_format.py
hypothesis_torch/module.py
hypothesis_torch/optim.py
hypothesis_torch/py.typed
hypothesis_torch/register_random_torch_state.py
hypothesis_torch/tensor.py
hypothesis_torch/utils.py
hypothesis_torch-2.0.6.dist-info/licenses/LICENSE
hypothesis_torch-2.0.6.dist-info/METADATA
hypothesis_torch-2.0.6.dist-info/WHEEL
hypothesis_torch-2.0.6.dist-info/entry_points.txt
hypothesis_torch-2.0.6.dist-info/top_level.txt
hypothesis_torch-2.0.6.dist-info/RECORD
