Metadata-Version: 2.4
Name: hypothesis-torch
Version: 2.0.6
Summary: Hypothesis strategies for various Pytorch structures, including tensors and modules.
Author-email: "Andrew P. Sansom" <andrew@euleriancircuit.com>
License: MIT License
Project-URL: Homepage, https://github.com/qthequartermasterman/hypothesis-torch
Project-URL: Documentation, https://hypothesis-torch.readthedocs.io/en/stable/
Project-URL: Repository, https://github.com/qthequartermasterman/hypothesis-torch.git
Project-URL: Issues, https://github.com/qthequartermasterman/hypothesis-torch/issues
Keywords: hypothesis,torch,pytorch,testing,property-based testing,deep learning,tensor,neural network,artificial intelligence,machine learning
Classifier: Development Status :: 5 - Production/Stable
Classifier: Intended Audience :: Developers
Classifier: Framework :: Hypothesis
Classifier: License :: OSI Approved :: MIT License
Classifier: Programming Language :: Python
Classifier: Programming Language :: Python :: 3
Classifier: Programming Language :: Python :: 3.9
Classifier: Programming Language :: Python :: 3.10
Classifier: Programming Language :: Python :: 3.11
Classifier: Programming Language :: Python :: 3.12
Classifier: Programming Language :: Python :: 3.13
Classifier: Topic :: Software Development :: Testing
Classifier: Topic :: Scientific/Engineering
Classifier: Topic :: Scientific/Engineering :: Artificial Intelligence
Classifier: Topic :: Scientific/Engineering :: Mathematics
Classifier: Topic :: Software Development
Classifier: Topic :: Software Development :: Libraries
Classifier: Topic :: Software Development :: Libraries :: Python Modules
Requires-Python: <3.14,>=3.9
License-File: LICENSE
Requires-Dist: hypothesis>=6.0.0
Requires-Dist: torch<3,>=2.4.0
Provides-Extra: huggingface
Requires-Dist: transformers<=4.57.0,>=4.42.3; extra == "huggingface"
Provides-Extra: dev
Requires-Dist: mypy==1.18.2; extra == "dev"
Requires-Dist: ruff==0.13.3; extra == "dev"
Requires-Dist: pyright==1.1.406; extra == "dev"
Requires-Dist: pytest==8.4.2; extra == "dev"
Requires-Dist: pytest-cov==7.0.0; extra == "dev"
Provides-Extra: docs
Requires-Dist: mkdocs==1.6.1; extra == "docs"
Requires-Dist: mkdocstrings[python]==0.30.1; extra == "docs"
Requires-Dist: mkdocs-autolinks-plugin==0.7.1; extra == "docs"
Requires-Dist: mkdocs-material==9.6.21; extra == "docs"
Requires-Dist: mkdocs-snippets==1.3.2; extra == "docs"
Requires-Dist: mkdocs-exclude==1.0.2; extra == "docs"
Provides-Extra: numpy
Requires-Dist: numpy==2.0.1; python_version == "3.9" and extra == "numpy"
Requires-Dist: numpy==2.1.2; python_version >= "3.10" and extra == "numpy"
Provides-Extra: old-numpy
Requires-Dist: numpy==1.26.4; extra == "old-numpy"
Provides-Extra: torch
Requires-Dist: torch; extra == "torch"
Requires-Dist: numpy; extra == "torch"
Provides-Extra: torch2-4-1
Requires-Dist: torch==2.4.1; extra == "torch2-4-1"
Requires-Dist: hypothesis_torch[numpy]; extra == "torch2-4-1"
Provides-Extra: torch2-5-1
Requires-Dist: torch==2.5.1; extra == "torch2-5-1"
Requires-Dist: hypothesis_torch[numpy]; extra == "torch2-5-1"
Provides-Extra: torch2-6-0
Requires-Dist: torch==2.6.0; extra == "torch2-6-0"
Requires-Dist: hypothesis_torch[numpy]; extra == "torch2-6-0"
Provides-Extra: torch2-7-0
Requires-Dist: torch==2.7.0; extra == "torch2-7-0"
Requires-Dist: hypothesis_torch[numpy]; extra == "torch2-7-0"
Provides-Extra: torch2-8-0
Requires-Dist: torch==2.8.0; extra == "torch2-8-0"
Requires-Dist: hypothesis_torch[numpy]; extra == "torch2-8-0"
Dynamic: license-file
